{"cameraMode":{"drawMode":0,"name":"Shaded","section":"Shading Mode"},"sceneLighting":false,"audioPlay":false,"sceneViewState":{"m_AlwaysRefresh":false,"showFog":true,"showSkybox":false,"showFlares":true,"showImageEffects":true,"showParticleSystems":true,"showVisualEffectGraphs":true,"m_FxEnabled":false},"in2DMode":false,"pivot":{"x":-8.38506031036377,"y":3.74580717086792,"z":2.4519004821777345},"rotation":{"x":-0.03935698792338371,"y":0.8721327185630798,"z":-0.07107404619455338,"w":-0.4832162857055664},"size":13.348196983337403,"orthographic":false}